cbtope_2/__init__.py
cbtope_2/standalone.py
cbtope_2/models/__init__.py
cbtope_2/models/pssm_model.pkl
cbtope_2/models/pssm_rsa_model.pkl
cbtope_2-1.6.dist-info/METADATA
cbtope_2-1.6.dist-info/WHEEL
cbtope_2-1.6.dist-info/entry_points.txt
cbtope_2-1.6.dist-info/top_level.txt
cbtope_2-1.6.dist-info/RECORD
