Metadata-Version: 2.1
Name: cbtope_2
Version: 1.6
Summary: CBTope2: A tool for predicting interactivity of B-cell epitopes
Home-page: https://github.com/PandeyAnupma/Cbtope_2
Author: Nishant Kumar, GPS Raghava
Author-email: nishantk@iiitd.ac.in, raghava@iiitd.ac.in
Requires-Python: >=3.7
Requires-Dist: joblib
Requires-Dist: openpyxl
Requires-Dist: Bio
